lib/Vanshika.py
lib/__init__.py
Topsis_Vanshika_102103484-0.0.1.dist-info/METADATA
Topsis_Vanshika_102103484-0.0.1.dist-info/WHEEL
Topsis_Vanshika_102103484-0.0.1.dist-info/top_level.txt
Topsis_Vanshika_102103484-0.0.1.dist-info/RECORD
