Metadata-Version: 2.1
Name: Topsis_Vanshika_102103484
Version: 0.0.1
Summary: topsis package for decision making
Author: Vanshika
Author-email: vmittal_be21@thapar.edu
Keywords: python,video,stream,video stream,camera stream,sockets
Classifier: Development Status :: 1 - Planning
Classifier: Intended Audience :: Developers
Classifier: Programming Language :: Python :: 3
Classifier: Operating System :: Unix
Classifier: Operating System :: MacOS :: MacOS X
Classifier: Operating System :: Microsoft :: Windows
Requires-Dist: logging
Requires-Dist: numpy
Requires-Dist: pandas
